aiolimit/__init__.py
aiolimit/aiolimit.py
aiolimit-0.0.3.dist-info/METADATA
aiolimit-0.0.3.dist-info/RECORD
aiolimit-0.0.3.dist-info/WHEEL
aiolimit-0.0.3.dist-info/top_level.txt
