Metadata-Version: 2.1
Name: aiolimit
Version: 0.0.3
Summary: async api limit
Home-page: https://github.com/jiamo/aiolimit
Author: jiamo
Author-email: life.130815@gmail.com
Maintainer: jiamo
Maintainer-email: life.130815@gmail.com
License: MIT
Platform: UNKNOWN
Classifier: License :: OSI Approved :: MIT License
Classifier: Framework :: AsyncIO
Classifier: Intended Audience :: Developers
Classifier: Programming Language :: Python :: 3.6
Classifier: Programming Language :: Python :: 3.7
Requires-Python: >=3.6
Requires-Dist: aioredis
